ns/__init__.py
ns/app.py
ns/config.py
ns/send.py
ntfy_send-0.4.1.dist-info/LICENSE
ntfy_send-0.4.1.dist-info/METADATA
ntfy_send-0.4.1.dist-info/WHEEL
ntfy_send-0.4.1.dist-info/entry_points.txt
ntfy_send-0.4.1.dist-info/RECORD
