Metadata-Version: 2.1
Name: ntfy-send
Version: 0.4.1
Summary: Client application for ntfy.sh
Home-page: https://git.goral.net.pl/mgoral/ntfy-send
License: GPLv3
Author: Michal Goral
Author-email: dev@goral.net.pl
Requires-Python: >=3.8,<4.0
Classifier: Development Status :: 3 - Alpha
Classifier: Environment :: Console
Classifier: Intended Audience :: End Users/Desktop
Classifier: License :: OSI Approved :: GNU General Public License v3 (GPLv3)
Classifier: License :: Other/Proprietary License
Classifier: Natural Language :: English
Classifier: Operating System :: POSIX
Classifier: Programming Language :: Python :: 3
Classifier: Programming Language :: Python :: 3.8
Classifier: Programming Language :: Python :: 3.9
Classifier: Programming Language :: Python :: 3.10
Classifier: Programming Language :: Python :: 3.11
Classifier: Topic :: Utilities
Requires-Dist: requests (>=2.28.1,<3.0.0)
Requires-Dist: tomlkit (>=0.11.6,<0.12.0)
Project-URL: Repository, https://git.goral.net.pl/mgoral/ntfy-send
